{"assets/fonts/Alata-Regular.ttf":["assets/fonts/Alata-Regular.ttf"],"assets/icons/cart.png":["assets/icons/cart.png"],"assets/images/movel1.jpg":["assets/images/movel1.jpg"],"assets/images/movel2.jpg":["assets/images/movel2.jpg"],"assets/images/movel3.jpg":["assets/images/movel3.jpg"],"assets/images/movel4.jpg":["assets/images/movel4.jpg"],"assets/images/movel5.jpg":["assets/images/movel5.jpg"],"assets/images/movel6.jpg":["assets/images/movel6.jpg"],"assets/images/movel7.jpg":["assets/images/movel7.jpg"],"packages/cupertino_icons/assets/CupertinoIcons.ttf":["packages/cupertino_icons/assets/CupertinoIcons.ttf"]}